qurix/__init__.py
qurix/kafka/__init__.py
qurix/kafka/utils/__init__.py
qurix/kafka/utils/__version__.py
qurix/kafka/utils/anonymizer.py
qurix/kafka/utils/generic_consumer.py
qurix/kafka/utils/kafka_observer.py
qurix/kafka/utils/offset_enum.py
tests/__init__.py
tests/test_anonymizer.py
tests/test_generic_consumer.py
tests/test_kafka_observer.py
qurix_kafka_utils-1.6.0.dist-info/METADATA
qurix_kafka_utils-1.6.0.dist-info/WHEEL
qurix_kafka_utils-1.6.0.dist-info/top_level.txt
qurix_kafka_utils-1.6.0.dist-info/RECORD
