Metadata-Version: 2.1
Name: qurix-kafka-utils
Version: 1.6.0
Summary: qurix generic utils for kafka
Home-page: https://github.com/qurixtechnology/qurix-kafka-utils.git
Author: qurix Technology
Keywords: python
Requires-Python: >=3.10, <4
Requires-Dist: confluent-kafka
Provides-Extra: dev
Requires-Dist: pytest ==7.3.1 ; extra == 'dev'
Requires-Dist: flake8 ==6.0.0 ; extra == 'dev'
Requires-Dist: pytest-flake8 ==1.1.1 ; extra == 'dev'
Requires-Dist: pytest-cov ==4.0.0 ; extra == 'dev'
Requires-Dist: wheel ==0.40.0 ; extra == 'dev'
Requires-Dist: twine ==4.0.2 ; extra == 'dev'
